fec_to_sqlite/__init__.py
fec_to_sqlite/cli.py
fec_to_sqlite/utils.py
fec_to_sqlite-0.2.dist-info/LICENSE
fec_to_sqlite-0.2.dist-info/METADATA
fec_to_sqlite-0.2.dist-info/WHEEL
fec_to_sqlite-0.2.dist-info/entry_points.txt
fec_to_sqlite-0.2.dist-info/top_level.txt
fec_to_sqlite-0.2.dist-info/RECORD
