Metadata-Version: 2.1
Name: fec-to-sqlite
Version: 0.2
Summary: Save FEC campaign finance data to a SQLite database
Home-page: https://github.com/dogsheep/fec-to-sqlite
Author: Simon Willison
License: Apache License, Version 2.0
Platform: UNKNOWN
Requires-Dist: sqlite-utils
Requires-Dist: click
Requires-Dist: requests
Requires-Dist: fecfile
Requires-Dist: tqdm
Provides-Extra: test
Requires-Dist: pytest ; extra == 'test'
